
[{"content":" Welcome to my page # ","date":"6 July 2025","externalUrl":null,"permalink":"/","section":"","summary":" Welcome to my page # ","title":"","type":"page"},{"content":"","date":"6 July 2025","externalUrl":null,"permalink":"/posts/","section":"Posts","summary":"","title":"Posts","type":"posts"},{"content":" About Me # Graduate student passionate about operating systems, computer networking, and distributed systems with a focus on building high-performance, scalable, and fault-tolerant systems. Hands-on experience in developing features for CRM platforms, contributing to seamless user experiences and platform optimization.\n","externalUrl":null,"permalink":"/about/","section":"","summary":"About Me # Graduate student passionate about operating systems, computer networking, and distributed systems with a focus on building high-performance, scalable, and fault-tolerant systems.","title":"","type":"page"},{"content":"","externalUrl":null,"permalink":"/authors/","section":"Authors","summary":"","title":"Authors","type":"authors"},{"content":"","externalUrl":null,"permalink":"/categories/","section":"Categories","summary":"","title":"Categories","type":"categories"},{"content":"","externalUrl":null,"permalink":"/series/","section":"Series","summary":"","title":"Series","type":"series"},{"content":"","externalUrl":null,"permalink":"/tags/","section":"Tags","summary":"","title":"Tags","type":"tags"}]